<annotation>
	<folder>my-project-name</folder>
	<filename>1.jpg</filename>
	<path>/my-project-name/1.jpg</path>
	<source>
		<database>Unspecified</database>
	</source>
	<size>
		<width>827</width>
		<height>532</height>
		<depth>3</depth>
	</size>
	<object>
		<name>First Name</name>
		<pose>Unspecified</pose>
		<truncated>Unspecified</truncated>
		<difficult>Unspecified</difficult>
		<bndbox>
			<xmin>233</xmin>
			<ymin>49</ymin>
			<xmax>401</xmax>
			<ymax>81</ymax>
		</bndbox>
	</object>
	<object>
		<name>Last Name</name>
		<pose>Unspecified</pose>
		<truncated>Unspecified</truncated>
		<difficult>Unspecified</difficult>
		<bndbox>
			<xmin>233</xmin>
			<ymin>81</ymin>
			<xmax>382</xmax>
			<ymax>109</ymax>
		</bndbox>
	</object>
	<object>
		<name>DOB</name>
		<pose>Unspecified</pose>
		<truncated>Unspecified</truncated>
		<difficult>Unspecified</difficult>
		<bndbox>
			<xmin>232</xmin>
			<ymin>142</ymin>
			<xmax>407</xmax>
			<ymax>173</ymax>
		</bndbox>
	</object>
	<object>
		<name>ID Number</name>
		<pose>Unspecified</pose>
		<truncated>Unspecified</truncated>
		<difficult>Unspecified</difficult>
		<bndbox>
			<xmin>227</xmin>
			<ymin>232</ymin>
			<xmax>617</xmax>
			<ymax>268</ymax>
		</bndbox>
	</object>
	<object>
		<name>Address</name>
		<pose>Unspecified</pose>
		<truncated>Unspecified</truncated>
		<difficult>Unspecified</difficult>
		<bndbox>
			<xmin>217</xmin>
			<ymin>344</ymin>
			<xmax>561</xmax>
			<ymax>417</ymax>
		</bndbox>
	</object>
</annotation>