<annotation><filename>1220.jpg</filename><size><width>702</width><height>425</height><depth>3</depth></size><object><name>First Name</name><bndbox><xmin>232</xmin><ymin>42</ymin><xmax>346</xmax><ymax>63</ymax></bndbox></object><object><name>Last Name</name><bndbox><xmin>233</xmin><ymin>66</ymin><xmax>414</xmax><ymax>95</ymax></bndbox></object><object><name>DOB</name><bndbox><xmin>233</xmin><ymin>117</ymin><xmax>344</xmax><ymax>143</ymax></bndbox></object><object><name>ID Number</name><bndbox><xmin>240</xmin><ymin>192</ymin><xmax>464</xmax><ymax>222</ymax></bndbox></object></annotation>