<annotation><filename>1297.jpg</filename><size><width>799</width><height>521</height><depth>3</depth></size><object><name>First Name</name><bndbox><xmin>196</xmin><ymin>126</ymin><xmax>292</xmax><ymax>199</ymax></bndbox></object><object><name>Last Name</name><bndbox><xmin>212</xmin><ymin>112</ymin><xmax>377</xmax><ymax>225</ymax></bndbox></object><object><name>DOB</name><bndbox><xmin>239</xmin><ymin>182</ymin><xmax>357</xmax><ymax>266</ymax></bndbox></object><object><name>ID Number</name><bndbox><xmin>315</xmin><ymin>155</ymin><xmax>579</xmax><ymax>327</ymax></bndbox></object></annotation>