<annotation><filename>1321.jpeg</filename><size><width>695</width><height>426</height><depth>3</depth></size><object><name>First Name</name><bndbox><xmin>248</xmin><ymin>27</ymin><xmax>380</xmax><ymax>115</ymax></bndbox></object><object><name>Last Name</name><bndbox><xmin>211</xmin><ymin>106</ymin><xmax>365</xmax><ymax>207</ymax></bndbox></object><object><name>Country</name><bndbox><xmin>244</xmin><ymin>213</ymin><xmax>365</xmax><ymax>298</ymax></bndbox></object><object><name>ID Number</name><bndbox><xmin>159</xmin><ymin>231</ymin><xmax>320</xmax><ymax>336</ymax></bndbox></object><object><name>DOB</name><bndbox><xmin>310</xmin><ymin>297</ymin><xmax>421</xmax><ymax>379</ymax></bndbox></object></annotation>