<annotation><filename>1525.jpeg</filename><size><width>640</width><height>413</height><depth>3</depth></size><object><name>First Name</name><bndbox><xmin>215</xmin><ymin>32</ymin><xmax>367</xmax><ymax>130</ymax></bndbox></object><object><name>Last Name</name><bndbox><xmin>187</xmin><ymin>107</ymin><xmax>363</xmax><ymax>215</ymax></bndbox></object><object><name>Country</name><bndbox><xmin>216</xmin><ymin>207</ymin><xmax>377</xmax><ymax>307</ymax></bndbox></object><object><name>DOB</name><bndbox><xmin>282</xmin><ymin>286</ymin><xmax>378</xmax><ymax>355</ymax></bndbox></object><object><name>ID Number</name><bndbox><xmin>132</xmin><ymin>218</ymin><xmax>267</xmax><ymax>306</ymax></bndbox></object></annotation>